comunio/__init__.py
comunio/main.py
comunio/metadata.py
comunio/calc/StatisticsCalculator.py
comunio/calc/__init__.py
comunio/credentials/CredentialsManager.py
comunio/credentials/__init__.py
comunio/database/DatabaseManager.py
comunio/database/SqlQueries.py
comunio/database/__init__.py
comunio/scraper/ComunioFetcher.py
comunio/scraper/ComunioSession.py
comunio/scraper/__init__.py
comunio/ui/LoginScreen.py
comunio/ui/StatisticsViewer.py
comunio/ui/__init__.py
comunio/ui/dialogs/__init__.py
comunio/ui/dialogs/login.py
comunio/ui/windows/__init__.py
comunio/ui/windows/stats.py
comunio-0.5.1.data/scripts/comunio
comunio-0.5.1.data/scripts/comunio-viewer
comunio-0.5.1.dist-info/DESCRIPTION.rst
comunio-0.5.1.dist-info/METADATA
comunio-0.5.1.dist-info/RECORD
comunio-0.5.1.dist-info/WHEEL
comunio-0.5.1.dist-info/metadata.json
comunio-0.5.1.dist-info/top_level.txt
