Metadata-Version: 2.0
Name: comunio
Version: 0.5.1
Summary: A python program that keeps track of a user's comunio profile
Home-page: https://gitlab.namibsun.net/namboy94/comunio-manager
Author: Hermann Krumrey
Author-email: hermann@krumreyh.com
License: GNU GPL3
Download-URL: https://gitlab.namibsun.net/namboy94/comunio-manager/repository/archive.zip?ref=master
Platform: UNKNOWN
Classifier: Environment :: Console
Classifier: Natural Language :: English
Classifier: Programming Language :: Python
Classifier: Topic :: Database :: Front-Ends
Classifier: Intended Audience :: Developers
Classifier: Development Status :: 3 - Alpha
Classifier: Operating System :: OS Independent
Classifier: License :: OSI Approved :: GNU General Public License v3 (GPLv3)
Requires-Dist: bs4
Requires-Dist: matplotlib
Requires-Dist: raven
Requires-Dist: requests
Provides-Extra: gui
Requires-Dist: PyQt5; extra == 'gui'
